iam_client/__init__.py
iam_client/client.py
iam_client/exceptions.py
iam_client/schemas.py
kavach_iam_client-0.1.0.dist-info/METADATA
kavach_iam_client-0.1.0.dist-info/WHEEL
kavach_iam_client-0.1.0.dist-info/top_level.txt
kavach_iam_client-0.1.0.dist-info/RECORD
