Metadata-Version: 2.4
Name: kavach-iam-client
Version: 0.1.0
Summary: Official IAM client for Kavach IAM
Requires-Python: >=3.10
Requires-Dist: requests>=2.31.0
Requires-Dist: pydantic>=2.5.0
